OneLibrary/__init__.py
OneLibrary-0.0.1.dist-info/LICENSE
OneLibrary-0.0.1.dist-info/METADATA
OneLibrary-0.0.1.dist-info/WHEEL
OneLibrary-0.0.1.dist-info/top_level.txt
OneLibrary-0.0.1.dist-info/RECORD
