Metadata-Version: 2.1
Name: OneLibrary
Version: 0.0.1
Summary: A new library
Home-page: https://github.com/jhlopezm
Author: Jorge Lopez
Author-email: jhlopezm2@gmail.com
License: UNKNOWN
Project-URL: Bug Tracker, https://github.com/pypa/sampleproject/issues
Platform: UNKNOWN
Classifier: Programming Language :: Python :: 3
Classifier: License :: OSI Approved :: MIT License
Classifier: Operating System :: OS Independent
Requires-Python: >=3.6
